gusina/__init__.py
gusina/core.py
Gusina-0.0.0.dev0.dist-info/METADATA
Gusina-0.0.0.dev0.dist-info/WHEEL
Gusina-0.0.0.dev0.dist-info/top_level.txt
Gusina-0.0.0.dev0.dist-info/RECORD
